{
  "timestamp": "2026-04-13T08:48:38Z",
  "timestamp_local": "2026-04-13 11:48 AM ",
  "phase": "PHASE-2",
  "system": {
    "hostname": "ahie",
    "os": "Linux 6.8.0-106-generic",
    "cpu_cores": 4,
    "load_average_1m": 2.62,
    "load_percent_of_cores": 65.5,
    "cpu_breakdown": {
      "user": 21,
      "system": 5,
      "idle": 73,
      "iowait": 1
    }
  },
  "memory": {
    "total_bytes": 13262778368,
    "total_gib": 12.35,
    "available_bytes": 4491743232,
    "available_gib": 4.18,
    "used_bytes": 8771035136,
    "oracle_available_bytes": 4491743232,
    "oracle_reserve_bytes": 1610612736,
    "oracle_healthy": true,
    "swap_free_bytes": 1105813504,
    "usage_percent": 66.1
  },
  "docker": {
    "memory_used_bytes": 2777371639,
    "memory_used_gib": 2.59,
    "ceiling_bytes": 6631389184,
    "ceiling_gib": 6.2,
    "ceiling_percent_of_system": 50,
    "usage_percent_of_ceiling": 41.9,
    "healthy": true,
    "container_count": 19
  },
  "thresholds": {
    "docker_memory_ceiling_bytes": 6631389184,
    "intervention_load_percent": 65,
    "oracle_reserve_bytes": 1610612736,
    "swap_policy": "emergency_only"
  },
  "top_cpu_processes": [
    {
      "pid": "29915",
      "cpu": "16.9",
      "mem_mb": "668620",
      "cmd": "/snap/firefox/8054/usr/lib/firefox/firefox"
    },
    {
      "pid": "30961",
      "cpu": "11.2",
      "mem_mb": "773760",
      "cmd": "/snap/firefox/8054/usr/lib/firefox/firefox -contentproc -isForBrowser -prefsHandle 0:32233 -prefMapHandle 1:284132 -jsInitHandle 2:156136 -parentBuildID 20260324124100 -sandboxReporter 3 -chrootClient 4 -ipcHandle 5 -initialChannelId {4779256a-e5a1-4c7f-b4e4-1e6d8dfba27c} -parentPid 29915 -crashReporter 6 -crashHelper 7 -greomni /snap/firefox/8054/usr/lib/firefox/omni.ja -appomni /snap/firefox/8054/usr/lib/firefox/browser/omni.ja -appDir /snap/firefox/8054/usr/lib/firefox/browser 6 tab"
    },
    {
      "pid": "187756",
      "cpu": "7.2",
      "mem_mb": "321412",
      "cmd": "/snap/firefox/8054/usr/lib/firefox/firefox -contentproc -isForBrowser -prefsHandle 0:44104 -prefMapHandle 1:284132 -jsInitHandle 2:156136 -parentBuildID 20260324124100 -sandboxReporter 3 -chrootClient 4 -ipcHandle 5 -initialChannelId {15d93dde-e39d-4bb6-bf18-bd2250492404} -parentPid 29915 -crashReporter 6 -crashHelper 7 -greomni /snap/firefox/8054/usr/lib/firefox/omni.ja -appomni /snap/firefox/8054/usr/lib/firefox/browser/omni.ja -appDir /snap/firefox/8054/usr/lib/firefox/browser 59 tab"
    },
    {
      "pid": "30489",
      "cpu": "5.6",
      "mem_mb": "145540",
      "cmd": "/snap/firefox/8054/usr/lib/firefox/firefox -contentproc -parentBuildID 20260324124100 -prefsHandle 0:36884 -prefMapHandle 1:284132 -sandboxReporter 2 -chrootClient 3 -ipcHandle 4 -initialChannelId {4ffa52da-b7dc-4168-8793-f9670f0cc554} -parentPid 29915 -crashReporter 5 -crashHelper 6 -appDir /snap/firefox/8054/usr/lib/firefox/browser 4 rdd"
    },
    {
      "pid": "186931",
      "cpu": "4.9",
      "mem_mb": "481472",
      "cmd": "/snap/firefox/8054/usr/lib/firefox/firefox -contentproc -isForBrowser -prefsHandle 0:44104 -prefMapHandle 1:284132 -jsInitHandle 2:156136 -parentBuildID 20260324124100 -sandboxReporter 3 -chrootClient 4 -ipcHandle 5 -initialChannelId {fc013696-7c69-4930-8d97-b874195f3f0a} -parentPid 29915 -crashReporter 6 -crashHelper 7 -greomni /snap/firefox/8054/usr/lib/firefox/omni.ja -appomni /snap/firefox/8054/usr/lib/firefox/browser/omni.ja -appDir /snap/firefox/8054/usr/lib/firefox/browser 58 tab"
    }
  ],
  "top_mem_processes": [
    {
      "pid": "15088",
      "cpu": "872072",
      "mem_mb": "2.0",
      "cmd": "/usr/share/elasticsearch/jdk/bin/java -Des.networkaddress.cache.ttl=60 -Des.networkaddress.cache.negative.ttl=10 -Djava.security.manager=allow -XX:+AlwaysPreTouch -Xss1m -Djava.awt.headless=true -Dfile.encoding=UTF-8 -Djna.nosys=true -XX:-OmitStackTraceInFastThrow -Dio.netty.noUnsafe=true -Dio.netty.noKeySetOptimization=true -Dio.netty.recycler.maxCapacityPerThread=0 -Dlog4j.shutdownHookEnabled=false -Dlog4j2.disable.jmx=true -Dlog4j2.formatMsgNoLookups=true -Djava.locale.providers=SPI,COMPAT --add-opens=java.base/java.io=org.elasticsearch.preallocate --add-opens=org.apache.lucene.core/org.apache.lucene.store=org.elasticsearch.vec --enable-native-access=org.elasticsearch.nativeaccess -Des.cgroups.hierarchy.override=/ -XX:ReplayDataFile=logs/replay_pid%p.log -Djava.library.path=/usr/share/elasticsearch/lib/platform/linux-x64:/usr/java/packages/lib:/usr/lib64:/lib64:/lib:/usr/lib -Djna.library.path=/usr/share/elasticsearch/lib/platform/linux-x64:/usr/java/packages/lib:/usr/lib64:/lib64:/lib:/usr/lib -Des.distribution.type=docker -XX:+UnlockDiagnosticVMOptions -XX:G1NumCollectionsKeepPinned=10000000 -XX:+UseG1GC -Djava.io.tmpdir=/tmp/elasticsearch-10810757218683496399 --add-modules=jdk.incubator.vector -XX:+HeapDumpOnOutOfMemoryError -XX:+ExitOnOutOfMemoryError -XX:HeapDumpPath=data -XX:ErrorFile=logs/hs_err_pid%p.log -Xlog:gc*,gc+age=trace,safepoint:file=logs/gc.log:utctime,level,pid,tags:filecount=32,filesize=64m -Xms512m -Xmx512m -XX:MaxDirectMemorySize=268435456 -XX:G1HeapRegionSize=4m -XX:InitiatingHeapOccupancyPercent=30 -XX:G1ReservePercent=15 --module-path /usr/share/elasticsearch/lib --add-modules=jdk.net --add-modules=ALL-MODULE-PATH -m org.elasticsearch.server/org.elasticsearch.bootstrap.Elasticsearch"
    },
    {
      "pid": "30961",
      "cpu": "773760",
      "mem_mb": "11.2",
      "cmd": "/snap/firefox/8054/usr/lib/firefox/firefox -contentproc -isForBrowser -prefsHandle 0:32233 -prefMapHandle 1:284132 -jsInitHandle 2:156136 -parentBuildID 20260324124100 -sandboxReporter 3 -chrootClient 4 -ipcHandle 5 -initialChannelId {4779256a-e5a1-4c7f-b4e4-1e6d8dfba27c} -parentPid 29915 -crashReporter 6 -crashHelper 7 -greomni /snap/firefox/8054/usr/lib/firefox/omni.ja -appomni /snap/firefox/8054/usr/lib/firefox/browser/omni.ja -appDir /snap/firefox/8054/usr/lib/firefox/browser 6 tab"
    },
    {
      "pid": "11735",
      "cpu": "689288",
      "mem_mb": "2.9",
      "cmd": "/usr/share/logstash/jdk/bin/java -Xms1g -Xmx1g -Djava.awt.headless=true -Dfile.encoding=UTF-8 -Djruby.compile.invokedynamic=true -XX:+HeapDumpOnOutOfMemoryError -Djava.security.egd=file:/dev/urandom -Dlog4j2.isThreadContextMapInheritable=true -Dlogstash.jackson.stream-read-constraints.max-string-length=200000000 -Dlogstash.jackson.stream-read-constraints.max-number-length=10000 -Dls.cgroup.cpuacct.path.override=/ -Dls.cgroup.cpu.path.override=/ -Xmx256m -Xms256m -Djruby.regexp.interruptible=true -Djdk.io.File.enableADS=true --add-exports=jdk.compiler/com.sun.tools.javac.api=ALL-UNNAMED --add-exports=jdk.compiler/com.sun.tools.javac.file=ALL-UNNAMED --add-exports=jdk.compiler/com.sun.tools.javac.parser=ALL-UNNAMED --add-exports=jdk.compiler/com.sun.tools.javac.tree=ALL-UNNAMED --add-exports=jdk.compiler/com.sun.tools.javac.util=ALL-UNNAMED --add-opens=java.base/java.security=ALL-UNNAMED --add-opens=java.base/java.io=ALL-UNNAMED --add-opens=java.base/java.nio.channels=ALL-UNNAMED --add-opens=java.base/sun.nio.ch=ALL-UNNAMED --add-opens=java.management/sun.management=ALL-UNNAMED -Dio.netty.allocator.maxOrder=11 -cp /usr/share/logstash/vendor/jruby/lib/jruby.jar:/usr/share/logstash/logstash-core/lib/jars/checker-qual-3.33.0.jar:/usr/share/logstash/logstash-core/lib/jars/commons-codec-1.15.jar:/usr/share/logstash/logstash-core/lib/jars/commons-compiler-3.1.0.jar:/usr/share/logstash/logstash-core/lib/jars/commons-logging-1.2.jar:/usr/share/logstash/logstash-core/lib/jars/error_prone_annotations-2.18.0.jar:/usr/share/logstash/logstash-core/lib/jars/failureaccess-1.0.1.jar:/usr/share/logstash/logstash-core/lib/jars/google-java-format-1.15.0.jar:/usr/share/logstash/logstash-core/lib/jars/guava-32.1.2-jre.jar:/usr/share/logstash/logstash-core/lib/jars/httpclient-4.5.13.jar:/usr/share/logstash/logstash-core/lib/jars/httpcore-4.4.14.jar:/usr/share/logstash/logstash-core/lib/jars/jackson-annotations-2.15.3.jar:/usr/share/logstash/logstash-core/lib/jars/jackson-core-2.15.3.jar:/usr/share/logstash/logstash-core/lib/jars/jackson-databind-2.15.3.jar:/usr/share/logstash/logstash-core/lib/jars/jackson-dataformat-cbor-2.15.3.jar:/usr/share/logstash/logstash-core/lib/jars/janino-3.1.0.jar:/usr/share/logstash/logstash-core/lib/jars/javassist-3.29.0-GA.jar:/usr/share/logstash/logstash-core/lib/jars/jsr305-3.0.2.jar:/usr/share/logstash/logstash-core/lib/jars/jvm-options-parser-8.14.1.jar:/usr/share/logstash/logstash-core/lib/jars/listenablefuture-9999.0-empty-to-avoid-conflict-with-guava.jar:/usr/share/logstash/logstash-core/lib/jars/log4j-1.2-api-2.17.1.jar:/usr/share/logstash/logstash-core/lib/jars/log4j-api-2.17.1.jar:/usr/share/logstash/logstash-core/lib/jars/log4j-core-2.17.1.jar:/usr/share/logstash/logstash-core/lib/jars/log4j-jcl-2.17.1.jar:/usr/share/logstash/logstash-core/lib/jars/log4j-slf4j-impl-2.17.1.jar:/usr/share/logstash/logstash-core/lib/jars/logstash-core.jar:/usr/share/logstash/logstash-core/lib/jars/reflections-0.10.2.jar:/usr/share/logstash/logstash-core/lib/jars/slf4j-api-1.7.32.jar:/usr/share/logstash/logstash-core/lib/jars/snakeyaml-2.2.jar org.logstash.Logstash"
    },
    {
      "pid": "29915",
      "cpu": "668620",
      "mem_mb": "16.9",
      "cmd": "/snap/firefox/8054/usr/lib/firefox/firefox"
    },
    {
      "pid": "55314",
      "cpu": "541976",
      "mem_mb": "2.4",
      "cmd": "/snap/firefox/8054/usr/lib/firefox/firefox -contentproc -isForBrowser -prefsHandle 0:44103 -prefMapHandle 1:284132 -jsInitHandle 2:156136 -parentBuildID 20260324124100 -sandboxReporter 3 -chrootClient 4 -ipcHandle 5 -initialChannelId {707d99c7-4778-4574-8ad5-c930f782ee12} -parentPid 29915 -crashReporter 6 -crashHelper 7 -greomni /snap/firefox/8054/usr/lib/firefox/omni.ja -appomni /snap/firefox/8054/usr/lib/firefox/browser/omni.ja -appDir /snap/firefox/8054/usr/lib/firefox/browser 21 tab"
    }
  ],
  "containers": [
    {
      "name": "stack-duka-dao-app-1",
      "status": "",
      "cpu": "0.00%",
      "mem_usage": "33.17MiB / 12.35GiB",
      "mem_perc": "0.26%"
    },
    {
      "name": "logstash",
      "status": "",
      "cpu": "1.15%",
      "mem_usage": "690.9MiB / 12.35GiB",
      "mem_perc": "5.46%"
    },
    {
      "name": "grafana",
      "status": "",
      "cpu": "0.06%",
      "mem_usage": "64.58MiB / 12.35GiB",
      "mem_perc": "0.51%"
    },
    {
      "name": "keycloak",
      "status": "",
      "cpu": "0.10%",
      "mem_usage": "503.2MiB / 12.35GiB",
      "mem_perc": "3.98%"
    },
    {
      "name": "zookeeper",
      "status": "",
      "cpu": "0.13%",
      "mem_usage": "82.97MiB / 12.35GiB",
      "mem_perc": "0.66%"
    },
    {
      "name": "keycloak-db",
      "status": "",
      "cpu": "0.00%",
      "mem_usage": "31.72MiB / 12.35GiB",
      "mem_perc": "0.25%"
    },
    {
      "name": "redis",
      "status": "",
      "cpu": "0.49%",
      "mem_usage": "6.562MiB / 12.35GiB",
      "mem_perc": "0.05%"
    },
    {
      "name": "consul",
      "status": "",
      "cpu": "0.40%",
      "mem_usage": "40.57MiB / 12.35GiB",
      "mem_perc": "0.32%"
    },
    {
      "name": "prometheus",
      "status": "",
      "cpu": "0.00%",
      "mem_usage": "43.95MiB / 12.35GiB",
      "mem_perc": "0.35%"
    },
    {
      "name": "elasticsearch",
      "status": "",
      "cpu": "1.44%",
      "mem_usage": "884MiB / 12.35GiB",
      "mem_perc": "6.99%"
    },
    {
      "name": "kong-db",
      "status": "",
      "cpu": "0.00%",
      "mem_usage": "28.57MiB / 12.35GiB",
      "mem_perc": "0.23%"
    },
    {
      "name": "app-db",
      "status": "",
      "cpu": "5.19%",
      "mem_usage": "22.14MiB / 12.35GiB",
      "mem_perc": "0.18%"
    },
    {
      "name": "bridge_tracker",
      "status": "",
      "cpu": "0.44%",
      "mem_usage": "21.72MiB / 12.35GiB",
      "mem_perc": "0.17%"
    },
    {
      "name": "bridge_heartbeat",
      "status": "",
      "cpu": "0.40%",
      "mem_usage": "31.08MiB / 12.35GiB",
      "mem_perc": "0.25%"
    },
    {
      "name": "bridge_api",
      "status": "",
      "cpu": "0.44%",
      "mem_usage": "78.26MiB / 12.35GiB",
      "mem_perc": "0.62%"
    },
    {
      "name": "portainer",
      "status": "",
      "cpu": "0.00%",
      "mem_usage": "27.94MiB / 12.35GiB",
      "mem_perc": "0.22%"
    },
    {
      "name": "bridge_db",
      "status": "",
      "cpu": "0.00%",
      "mem_usage": "29.43MiB / 12.35GiB",
      "mem_perc": "0.23%"
    },
    {
      "name": "trusting_beaver",
      "status": "",
      "cpu": "0.11%",
      "mem_usage": "21.86MiB / 12.35GiB",
      "mem_perc": "0.17%"
    },
    {
      "name": "zerotier",
      "status": "",
      "cpu": "0.08%",
      "mem_usage": "6.086MiB / 12.35GiB",
      "mem_perc": "0.05%"
    }
  ]
}